.gitattributes
.gitignore
.pylintrc
LICENSE.txt
MANIFEST.in
README.md
makefile
pyproject.toml
requirements.txt
setup.py
docs/Makefile
docs/source/conf.py
docs/source/index.rst
docs/source/logo.svg
docs/source/figures/distributions/generate.sh
docs/source/figures/distributions/dipoles/0.svg
docs/source/figures/distributions/images/0.svg
docs/source/figures/distributions/wilkens/0.svg
docs/source/figures/restrictions/affine.svg
docs/source/figures/restrictions/generate.py
docs/source/figures/restrictions/none.svg
docs/source/figures/restrictions/positive.svg
docs/source/practice/index.rst
docs/source/practice/examples/configuration.rst
docs/source/practice/examples/index.rst
docs/source/practice/examples/vanilla.rst
docs/source/practice/formats/dislocation-sample.rst
docs/source/practice/formats/energy-evaluation.rst
docs/source/practice/formats/fourier-transform.rst
docs/source/practice/formats/index.rst
docs/source/practice/formats/model-adjustment.rst
docs/source/practice/formats/spatial-analysis.rst
docs/source/practice/installation/editable.rst
docs/source/practice/installation/index.rst
docs/source/practice/installation/regular.rst
docs/source/practice/installation/venv.rst
src/numlpa/__init__.py
src/numlpa/__main__.py
src/numlpa/_version.py
src/numlpa/api.py
src/numlpa/default.conf
src/numlpa.egg-info/PKG-INFO
src/numlpa.egg-info/SOURCES.txt
src/numlpa.egg-info/dependency_links.txt
src/numlpa.egg-info/entry_points.txt
src/numlpa.egg-info/requires.txt
src/numlpa.egg-info/top_level.txt
src/numlpa/core/__init__.py
src/numlpa/core/parallelism.py
src/numlpa/core/storage.py
src/numlpa/kits/__init__.py
src/numlpa/kits/analyzers/__init__.py
src/numlpa/kits/analyzers/cpu/__init__.py
src/numlpa/kits/analyzers/cpu/analysis.py
src/numlpa/kits/analyzers/cpu/interactionmodule.c
src/numlpa/kits/analyzers/cpu/parser.py
src/numlpa/kits/diffractometers/__init__.py
src/numlpa/kits/diffractometers/cpu/__init__.py
src/numlpa/kits/diffractometers/cpu/diffraction.py
src/numlpa/kits/diffractometers/cpu/displacementmodule.c
src/numlpa/kits/diffractometers/cpu/parser.py
src/numlpa/kits/distributions/__init__.py
src/numlpa/kits/distributions/dipoles.py
