Metadata-Version: 2.1
Name: numlpa
Version: 1.0.0b9
Summary: Numerical Line Profile Analysis package.
Author-email: Dunstan Becht <dunstan.becht@orange.fr>
Project-URL: Homepage, https://gitlab.com/x-rays/numlpa
Project-URL: Bug Tracker, https://gitlab.com/x-rays/numlpa/issues
Project-URL: Documentation, https://x-rays.gitlab.io/numlpa
Classifier: Programming Language :: Python :: 3
Classifier: License :: OSI Approved :: GNU General Public License v3 (GPLv3)
Requires-Python: <3.12,>=3.8
License-File: LICENSE.txt
Requires-Dist: numpy==1.24.2
Requires-Dist: scipy==1.10.1
Requires-Dist: matplotlib==3.7.0
